fdm/__init__.py
fdm/_version.py
fdm/fdm.py
fdm/multivariate.py
fdm/numerics.py
fdm-0.5.0.dist-info/METADATA
fdm-0.5.0.dist-info/WHEEL
fdm-0.5.0.dist-info/licenses/LICENCE.txt
fdm-0.5.0.dist-info/RECORD
