Metadata-Version: 2.3
Name: fdm
Version: 0.5.0
Summary: Estimate derivatives with finite differences
Project-URL: repository, https://github.com/wesselb/fdm
Author-email: Wessel Bruinsma <wessel.p.bruinsma@gmail.com>
License: MIT
Keywords: finite-difference,python
Classifier: Development Status :: 5 - Production/Stable
Classifier: Programming Language :: Python :: 3
Requires-Python: >=3.6
Requires-Dist: numpy>=1.16
Requires-Dist: sympy
Provides-Extra: dev
Requires-Dist: build; extra == 'dev'
Requires-Dist: coveralls; extra == 'dev'
Requires-Dist: ghp-import; extra == 'dev'
Requires-Dist: ipython; extra == 'dev'
Requires-Dist: jupyter-book; extra == 'dev'
Requires-Dist: mypy; extra == 'dev'
Requires-Dist: numpy; extra == 'dev'
Requires-Dist: pre-commit; extra == 'dev'
Requires-Dist: pyright>=1.1.331; extra == 'dev'
Requires-Dist: pytest-cov; extra == 'dev'
Requires-Dist: pytest>=6; extra == 'dev'
Requires-Dist: ruff; extra == 'dev'
Requires-Dist: sybil; extra == 'dev'
Requires-Dist: tox; extra == 'dev'
Requires-Dist: wheel; extra == 'dev'
